{
	"hardware": [
		{
			"title": "iPhone 13 Mini"
		},
		{
			"title": "MacBook Air M2"
		},
		{
			"title": "AirPods Pro (2nd Gen)"
		},
		{
			"title": "Apple Watch SE (1st Gen)"
		},
		{
			"title": "Apple TV 4K (2nd Gen)"
		}
	],
	"services": [
		{
			"title": "Vercel",
			"url": "https://vercel.com",
			"category": "hosting"
		}
	],
	"other": [
		{
			"title": "MonoLisa",
			"url": "https://monolisa.dev",
			"category": "dev font"
		},
		{
			"title": "Geist",
			"url": "https://vercel.com/font",
			"category": "web font"
		}
	]
}
